[
    {
        "ComputerName":  "ADMIN",
        "TargetIP":  "192.168.22.221",
        "AdapterName":  "Wi-Fi",
        "PropertyDisplayName":  "Channel Width for 6GHz",
        "RegistryKeyword":  "ChannelWidth6",
        "OriginalValue":  "Auto",
        "OriginalRegistryValue":  "1",
        "TargetValue":  "20 MHz Only",
        "FinalValue":  "20 MHz Only",
        "FinalRegistryValue":  "0",
        "ApplyAttempted":  true,
        "ApplySucceeded":  true,
        "VerificationSucceeded":  true,
        "ExecutionMode":  "WriteOnly",
        "TargetValueType":  "DisplayValue",
        "RestartAttempted":  false,
        "RestartSucceeded":  null,
        "Notes":  "",
        "PSComputerName":  "192.168.22.221",
        "RunspaceId":  "28f76bc3-f426-4a9a-9fac-676733a632e6",
        "PSShowComputerName":  true
    },
    {
        "ComputerName":  "DESKTOP-9LSD789",
        "TargetIP":  "192.168.22.222",
        "AdapterName":  "Wi-Fi 6",
        "PropertyDisplayName":  "Channel Width for 6GHz",
        "RegistryKeyword":  "ChannelWidth6",
        "OriginalValue":  "Auto",
        "OriginalRegistryValue":  "1",
        "TargetValue":  "20 MHz Only",
        "FinalValue":  "20 MHz Only",
        "FinalRegistryValue":  "0",
        "ApplyAttempted":  true,
        "ApplySucceeded":  true,
        "VerificationSucceeded":  true,
        "ExecutionMode":  "WriteOnly",
        "TargetValueType":  "DisplayValue",
        "RestartAttempted":  false,
        "RestartSucceeded":  null,
        "Notes":  "",
        "PSComputerName":  "192.168.22.222",
        "RunspaceId":  "66caef8a-7b66-43b8-9d23-33c9304b6cc6",
        "PSShowComputerName":  true
    }
]
